braceexpand.py
braceexpand-0.1.5.dist-info/DESCRIPTION.rst
braceexpand-0.1.5.dist-info/METADATA
braceexpand-0.1.5.dist-info/RECORD
braceexpand-0.1.5.dist-info/WHEEL
braceexpand-0.1.5.dist-info/metadata.json
braceexpand-0.1.5.dist-info/top_level.txt
