Metadata-Version: 1.1
Name: braceexpand
Version: 0.1.5
Summary: Bash-style brace expansion for Python
Home-page: https://github.com/trendels/braceexpand
Author: Stanis Trendelenburg
Author-email: stanis.trendelenburg@gmail.com
License: MIT
Platform: UNKNOWN
Classifier: License :: OSI Approved :: MIT License
Classifier: Programming Language :: Python
Classifier: Programming Language :: Python :: 2
Classifier: Programming Language :: Python :: 2.7
Classifier: Programming Language :: Python :: 3
Classifier: Programming Language :: Python :: 3.5
Classifier: Programming Language :: Python :: 3.6
Classifier: Programming Language :: Python :: 3.7
